{
  "$schema": "https://docs.renovatebot.com/renovate-schema.json",
  // This is a configuration file for Renovate Bot that's available to us as part of Konflux.
  // See docs: https://redhat-appstudio.github.io/docs.appstudio.io/Documentation/main/concepts/RenovateBot/

  "extends": [
    "config:base"
  ],
  "timezone": "Etc/UTC",
  "schedule": [
    // Allowed syntax: https://docs.renovatebot.com/configuration-options/#schedule
    // The time was selected (with the help of https://time.fyi/timezones) so that Renovate isn't active during
    // business hours in Germany and US West Coast. This way, after we merge a PR, a new one does not pop up immediately
    // after that.
    "after 3am and before 7am",
  ],
  "tekton": {
    "fileMatch": [
      "\\.yaml$",
      "\\.yml$",
    ],
    "includePaths": [
      ".tekton/**",
    ],
    "pinDigests": true,
  },
}
