{
  "id": "d3e480c1-c6de-4cd2-9006-9a3eb3ad36b6",
  "name": "Required Image Label",
  "severity": "LOW_SEVERITY",
  "lifecycle_stages": [
    "BUILD",
    "DEPLOY"
  ],
  "description": "Alert on deployments with images missing the specified label.",
  "rationale": "Only images with the specified label should be deployed to ensure all deployments contain approved images.",
  "remediation": "Request that the maintainer add the required label to the image.",
  "categories": [
    "DevOps Best Practices",
    "Security Best Practices"
  ],
  "fields": {
    "requiredImageLabel": {
      "key": "required-label.*",
      "value": "required-value.*"
    }
  },
  "whitelists": [
    {
      "name": "Don't alert on kube-system namespace",
      "deployment": {
        "scope": {
          "namespace": "kube-system"
        }
      }
    },
    {
      "name": "Don't alert on istio-system namespace",
      "deployment": {
        "scope": {
          "namespace": "istio-system"
        }
      }
    }
  ],
  "disabled": true
}
