{
  "id": "dce17697-1b72-49d2-b18a-05d893cd9368",
  "name": "Ensure That a User for the Container Has Been Created",
  "description": "Containers should run as a non-root user",
  "rationale": "It is good practice to run the container as a non-root user, where possible. This can be done via the USER directive in the Dockerfile.",
  "whitelists": [
    {
      "name": "Don't alert on StackRox namespace",
      "deployment": {
        "scope": {
          "namespace": "stackrox"
        }
      }
    },
    {
      "name": "Don't alert on kube-system namespace",
      "deployment": {
        "scope": {
          "namespace": "kube-system"
        }
      }
    }
  ],
  "remediation": "Ensure that the Dockerfile for each container switches from the root user",
  "categories": [
    "DevOps Best Practices",
    "Security Best Practices"
  ],
  "lifecycleStages": [
    "BUILD",
    "DEPLOY"
  ],
  "severity": "LOW_SEVERITY",
  "policyVersion": "1",
  "policySections": [
    {
      "sectionName": "",
      "policyGroups": [
        {
          "fieldName": "Image User",
          "booleanOperator": "OR",
          "negate": false,
          "values": [
            {
              "value": "0"
            },
            {
              "value": "root"
            }
          ]
        }
      ]
    }
  ]
}
